nukelib/__init__.py
nukelib-0.0.2b0.dist-info/METADATA
nukelib-0.0.2b0.dist-info/WHEEL
nukelib-0.0.2b0.dist-info/top_level.txt
nukelib-0.0.2b0.dist-info/RECORD
