Metadata-Version: 2.1
Name: nukelib
Version: 0.0.2b0
Summary: Discord accounts nukker lib
Home-page: UNKNOWN
Author: Aniko (Aniko#0104)
Author-email: <mail@aniko.com>
License: UNKNOWN
Keywords: python,discord api,discord nuke,nuke,discord,discord token
Platform: UNKNOWN
Classifier: Development Status :: 1 - Planning
Classifier: Intended Audience :: Developers
Classifier: Programming Language :: Python :: 3
Classifier: Operating System :: Unix
Classifier: Operating System :: MacOS :: MacOS X
Classifier: Operating System :: Microsoft :: Windows
Requires-Dist: requests
